xprint/__init__.py
xprintlog/__init__.py
xprintlog-0.0.2.dist-info/METADATA
xprintlog-0.0.2.dist-info/WHEEL
xprintlog-0.0.2.dist-info/top_level.txt
xprintlog-0.0.2.dist-info/RECORD
