Metadata-Version: 2.1
Name: xprintlog
Version: 0.0.2
Summary: Patch your print function.
Home-page: https://github.com/dwpeng/xprint
Author: dwpeng
Author-email: 1732889554@qq.com
Maintainer: dwpeng
Maintainer-email: 1732889554@qq.com
License: UNKNOWN
Keywords: print,logging,log
Platform: UNKNOWN
Classifier: Development Status :: 4 - Beta
Classifier: Operating System :: OS Independent
Classifier: Intended Audience :: Developers
Classifier: License :: OSI Approved :: BSD License
Classifier: Programming Language :: Python
Classifier: Programming Language :: Python :: Implementation
Classifier: Programming Language :: Python :: 2
Classifier: Programming Language :: Python :: 2.7
Classifier: Programming Language :: Python :: 3
Classifier: Programming Language :: Python :: 3.4
Classifier: Programming Language :: Python :: 3.5
Classifier: Programming Language :: Python :: 3.6
Classifier: Topic :: Software Development :: Libraries
